simple_onnx_processing_tools/__init__.py
simple_onnx_processing_tools-1.1.32.dist-info/LICENSE
simple_onnx_processing_tools-1.1.32.dist-info/METADATA
simple_onnx_processing_tools-1.1.32.dist-info/WHEEL
simple_onnx_processing_tools-1.1.32.dist-info/top_level.txt
simple_onnx_processing_tools-1.1.32.dist-info/RECORD
