Metadata-Version: 2.1
Name: simple_onnx_processing_tools
Version: 1.1.32
Summary: A set of simple tools for splitting, merging, OP deletion, size compression, rewriting attributes and constants, OP generation, change opset, change to the specified input order, addition of OP, RGB to BGR conversion, change batch size, batch rename of OP, and JSON convertion for ONNX models.
Home-page: https://github.com/PINTO0309/simple-onnx-processing-tools
Author: Katsuya Hyodo
Author-email: rmsdh122@yahoo.co.jp
License: MIT License
Platform: linux
Platform: unix
Requires-Python: >=3.6
License-File: LICENSE
Requires-Dist: snc4onnx >=1.0.12
Requires-Dist: sne4onnx >=1.0.11
Requires-Dist: snd4onnx >=1.1.6
Requires-Dist: scs4onnx >=1.0.18
Requires-Dist: sog4onnx >=1.0.16
Requires-Dist: sam4onnx >=1.0.14
Requires-Dist: soc4onnx >=1.0.2
Requires-Dist: scc4onnx >=1.0.5
Requires-Dist: sna4onnx >=1.0.6
Requires-Dist: sbi4onnx >=1.0.5
Requires-Dist: sor4onnx >=1.0.5
Requires-Dist: sit4onnx >=1.0.7
Requires-Dist: onnx2json >=2.0.4
Requires-Dist: json2onnx >=2.0.3
Requires-Dist: sed4onnx >=1.0.5
Requires-Dist: soa4onnx >=1.0.4
Requires-Dist: sod4onnx >=1.0.0
Requires-Dist: ssi4onnx >=1.0.2
Requires-Dist: ssc4onnx >=1.0.5
Requires-Dist: sio4onnx >=1.0.2
Requires-Dist: svs4onnx >=1.0.0
Requires-Dist: onnx2tf >=1.20.1
Requires-Dist: sng4onnx >=1.0.2
Requires-Dist: sde4onnx >=1.0.0
Requires-Dist: spo4onnx >=1.0.4
Provides-Extra: full
Requires-Dist: onnx-simplifier ; extra == 'full'
Requires-Dist: rich ; extra == 'full'
